deepframe/__init__.py
deepframe/deepframe.cpython-310-aarch64-linux-gnu.so
deepframe-0.1.1.dist-info/licenses/LICENSE
deepframe-0.1.1.dist-info/METADATA
deepframe-0.1.1.dist-info/WHEEL
deepframe-0.1.1.dist-info/top_level.txt
deepframe-0.1.1.dist-info/RECORD
