Metadata-Version: 2.4
Name: deepframe
Version: 0.1.1
Author: activeloop.ai
Author-email: support@activeloop.ai
Project-URL: Source, https://github.com/activeloopai/deepframe
License-File: LICENSE
Requires-Dist: numpy
Dynamic: author
Dynamic: author-email
Dynamic: description
Dynamic: description-content-type
Dynamic: license-file
Dynamic: project-url
Dynamic: requires-dist
